celeste_image_intelligence/__init__.py
celeste_image_intelligence/client.py
celeste_image_intelligence/io.py
celeste_image_intelligence/models.py
celeste_image_intelligence/parameters.py
celeste_image_intelligence/py.typed
celeste_image_intelligence/streaming.py
celeste_image_intelligence/providers/__init__.py
celeste_image_intelligence/providers/google/__init__.py
celeste_image_intelligence/providers/google/client.py
celeste_image_intelligence/providers/google/config.py
celeste_image_intelligence/providers/google/models.py
celeste_image_intelligence/providers/google/parameters.py
celeste_image_intelligence/providers/google/streaming.py
celeste_image_intelligence/providers/mistral/__init__.py
celeste_image_intelligence/providers/mistral/client.py
celeste_image_intelligence/providers/mistral/config.py
celeste_image_intelligence/providers/mistral/models.py
celeste_image_intelligence/providers/mistral/parameters.py
celeste_image_intelligence/providers/mistral/streaming.py
celeste_image_intelligence/providers/openai/__init__.py
celeste_image_intelligence/providers/openai/client.py
celeste_image_intelligence/providers/openai/config.py
celeste_image_intelligence/providers/openai/models.py
celeste_image_intelligence/providers/openai/parameters.py
celeste_image_intelligence/providers/openai/streaming.py
celeste_image_intelligence-0.2.3.dist-info/METADATA
celeste_image_intelligence-0.2.3.dist-info/WHEEL
celeste_image_intelligence-0.2.3.dist-info/entry_points.txt
celeste_image_intelligence-0.2.3.dist-info/RECORD
