Metadata-Version: 2.4
Name: celeste-image-intelligence
Version: 0.2.3
Summary: Type-safe image intelligence for Celeste AI. Unified interface for Google Gemini and more
Project-URL: Homepage, https://withceleste.ai
Project-URL: Documentation, https://withceleste.ai/docs
Project-URL: Repository, https://github.com/withceleste/celeste-python
Project-URL: Issues, https://github.com/withceleste/celeste-python/issues
Author-email: Kamilbenkirane <kamil@withceleste.ai>
License: Apache-2.0
Keywords: ai,gemini,google,image-analysis,image-intelligence,vision
Classifier: Development Status :: 3 - Alpha
Classifier: Intended Audience :: Developers
Classifier: License :: OSI Approved :: Apache Software License
Classifier: Operating System :: OS Independent
Classifier: Programming Language :: Python :: 3
Classifier: Programming Language :: Python :: 3.12
Classifier: Programming Language :: Python :: 3.13
Classifier: Topic :: Scientific/Engineering :: Artificial Intelligence
Classifier: Typing :: Typed
Requires-Python: >=3.12
